mistral_v0_2/__init__.py
mistral_v0_2/lib/__init__.py
mistral_v0_2/lib/array_conversion.py
mistral_v0_2/lib/collate_fn.py
mistral_v0_2/lib/example_data.py
mistral_v0_2/lib/generate.py
mistral_v0_2/model/__init__.py
mistral_v0_2/model/attention.py
mistral_v0_2/model/decoder.py
mistral_v0_2/model/decoder_block.py
mistral_v0_2/model/embedding.py
mistral_v0_2/model/kvcache.py
mistral_v0_2/model/mistral_lm.py
mistral_v0_2/model/mistral_model.py
mistral_v0_2/model/mlp_layer.py
mistral_v0_2/model/rms_norm.py
mistral_v0_2/model/rotary_embedding.py
mistral_v0.2_jax-0.0.1.dist-info/LICENSE
mistral_v0.2_jax-0.0.1.dist-info/METADATA
mistral_v0.2_jax-0.0.1.dist-info/WHEEL
mistral_v0.2_jax-0.0.1.dist-info/top_level.txt
mistral_v0.2_jax-0.0.1.dist-info/RECORD
