Metadata-Version: 2.1
Name: mistral-v0.2-jax
Version: 0.0.1
Summary: JAX implementation of the Mistral v0.2 base model.
Author-email: Shin <shin@yixiaoer.sg>
Project-URL: Repository, https://github.com/yixiaoer/mistral-v0.2-jax
Project-URL: Issues, https://github.com/yixiaoer/mistral-v0.2-jax/issues
Classifier: Development Status :: 4 - Beta
Classifier: Programming Language :: Python
Classifier: License :: OSI Approved :: MIT License
Requires-Python: >=3.12
License-File: LICENSE
Requires-Dist: jax
Requires-Dist: jaxlib
Requires-Dist: torch
Requires-Dist: transformers
Requires-Dist: datasets
Requires-Dist: einops
Requires-Dist: einshard <0.3,>=0.2.0
Requires-Dist: sentencepiece
Requires-Dist: accelerate
Requires-Dist: mypy
Requires-Dist: sphinx
Requires-Dist: sphinx-autobuild
Requires-Dist: sphinx-autodoc-typehints
Requires-Dist: sphinx-book-theme
